pymetkit/__init__.py
pymetkit/_version.py
pymetkit/metkit_c.h
pymetkit/pymetkit.py
pymetkit-1.16.0.9.dist-info/licenses/AUTHORS
pymetkit-1.16.0.9.dist-info/licenses/LICENSE
pymetkit-1.16.0.9.dist-info/licenses/NOTICE
pymetkit-1.16.0.9.dist-info/METADATA
pymetkit-1.16.0.9.dist-info/WHEEL
pymetkit-1.16.0.9.dist-info/top_level.txt
pymetkit-1.16.0.9.dist-info/RECORD
