Metadata-Version: 2.4
Name: pymetkit
Version: 1.16.0.9
Summary: Python interface for metkit
Author-email: "European Centre for Medium-Range Weather Forecasts (ECMWF)" <software.support@ecmwf.int>
License: Apache License Version 2.0
Requires-Python: >=3.10
License-File: LICENSE
License-File: NOTICE
License-File: AUTHORS
Requires-Dist: cffi
Requires-Dist: metkitlib
Requires-Dist: findlibs
Provides-Extra: tests
Requires-Dist: pytest; extra == "tests"
Dynamic: license-file
